cfn_docgen/__init__.py
cfn_docgen/config.py
cfn_docgen/adapters/__init__.py
cfn_docgen/adapters/cfn_document_storage.py
cfn_docgen/adapters/cfn_specification_repository.py
cfn_docgen/adapters/cfn_template_provider.py
cfn_docgen/adapters/internal/__init__.py
cfn_docgen/adapters/internal/cache.py
cfn_docgen/adapters/internal/file_loader.py
cfn_docgen/adapters/internal/tests/__init__.py
cfn_docgen/adapters/internal/tests/test_cache.py
cfn_docgen/adapters/internal/tests/test_file_loader.py
cfn_docgen/adapters/tests/__init__.py
cfn_docgen/adapters/tests/test_cfn_document_storage.py
cfn_docgen/adapters/tests/test_cfn_specification_repository.py
cfn_docgen/adapters/tests/test_cfn_template_provider.py
cfn_docgen/domain/__init__.py
cfn_docgen/domain/model/__init__.py
cfn_docgen/domain/model/cfn_document_generator.py
cfn_docgen/domain/model/cfn_specification.py
cfn_docgen/domain/model/cfn_template.py
cfn_docgen/domain/model/tests/__init__.py
cfn_docgen/domain/model/tests/test_all_resource_types_all_regions.py
cfn_docgen/domain/model/tests/test_cfn_document_generator.py
cfn_docgen/domain/model/tests/test_cfn_specification.py
cfn_docgen/domain/model/tests/test_cfn_template.py
cfn_docgen/domain/ports/__init__.py
cfn_docgen/domain/ports/cache.py
cfn_docgen/domain/ports/cfn_document_storage.py
cfn_docgen/domain/ports/cfn_specification_repository.py
cfn_docgen/domain/ports/cfn_template_provider.py
cfn_docgen/domain/ports/internal/__init__.py
cfn_docgen/domain/ports/internal/file_loader.py
cfn_docgen/domain/services/__init__.py
cfn_docgen/domain/services/cfn_docgen_service.py
cfn_docgen/domain/services/cfn_skeleton_service.py
cfn_docgen/domain/services/tests/__init__.py
cfn_docgen/domain/services/tests/test_cfn_docgen_service.py
cfn_docgen/domain/services/tests/test_cfn_skelton_service.py
cfn_docgen/entrypoints/__init__.py
cfn_docgen/entrypoints/cli/__init__.py
cfn_docgen/entrypoints/cli/main.py
cfn_docgen/entrypoints/cli/model/__init__.py
cfn_docgen-1.0.1.dist-info/LICENSE
cfn_docgen-1.0.1.dist-info/METADATA
cfn_docgen-1.0.1.dist-info/WHEEL
cfn_docgen-1.0.1.dist-info/entry_points.txt
cfn_docgen-1.0.1.dist-info/top_level.txt
cfn_docgen-1.0.1.dist-info/RECORD
